processmanager/ProcessBase.py
processmanager/ProcessRunner.py
processmanager/ScheduledProcess.py
processmanager/__init__.py
processmanager/error/ProcessRunProfileMissing.py
processmanager/error/__init__.py
processmanager/reporter/ProcessReporter.py
processmanager/reporter/__init__.py
processmanager/termination/GracefulTermination.py
processmanager/termination/__init__.py
persuader_technology_automata_process_manager-0.2.2.dist-info/LICENSE
persuader_technology_automata_process_manager-0.2.2.dist-info/METADATA
persuader_technology_automata_process_manager-0.2.2.dist-info/WHEEL
persuader_technology_automata_process_manager-0.2.2.dist-info/top_level.txt
persuader_technology_automata_process_manager-0.2.2.dist-info/RECORD
