Metadata-Version: 2.1
Name: persuader-technology-automata-process-manager
Version: 0.2.2
Summary: Automata Process Manager
Author: Persuader Technology
Author-email: software@persuader.technology
License: UNLICENSE
Classifier: Programming Language :: Python :: 3
License-File: LICENSE
Requires-Dist: schedule (==1.1.0)
Requires-Dist: persuader-technology-automata-core (>=0.6.0)
Requires-Dist: persuader-technology-automata-utilities (>=0.2.1)
Requires-Dist: persuader-technology-automata-process-repository (>=0.2.1)
